quran_rofi/__init__.py
quran_rofi/config.py
quran_rofi/quran.py
quran_rofi/assets/Al Qalam Quran Majeed.ttf
quran_rofi/assets/contoh_confgi_quran-rofi.ini
quran_rofi/assets/quran.desktop
quran_rofi/assets/quran.png
quran_rofi/assets/murotal/README.md
quran_rofi-0.1.10.data/data/share/Quran/contoh_confgi_quran-rofi.ini
quran_rofi-0.1.10.data/data/share/Quran/murotal/README.md
quran_rofi-0.1.10.data/data/share/applications/quran.desktop
quran_rofi-0.1.10.data/data/share/fonts/Al Qalam Quran Majeed.ttf
quran_rofi-0.1.10.data/data/share/icons/quran.png
quran_rofi-0.1.10.dist-info/LICENSE
quran_rofi-0.1.10.dist-info/METADATA
quran_rofi-0.1.10.dist-info/WHEEL
quran_rofi-0.1.10.dist-info/entry_points.txt
quran_rofi-0.1.10.dist-info/top_level.txt
quran_rofi-0.1.10.dist-info/RECORD
