Metadata-Version: 2.1
Name: quran-rofi
Version: 0.1.10
Summary: Al-Quran dengan Terjemahan / Tafsir Jalalayn
Home-page: https://gitlab.com/nesstero/Al-Quran-Rofi
Author: nestero
Author-email: nestero@mail.com
License: MIT
Platform: UNKNOWN
License-File: LICENSE
Requires-Dist: pyrof
Requires-Dist: alquran-id
Requires-Dist: appdirs
Requires-Dist: pydub
